ssh2_python3.libs/libcrypto-92aa3375.so.1.1
ssh2_python3.libs/libssh2-205534d8.so.1.0.1
ssh2_python3-1.11.1.dist-info/RECORD
ssh2_python3-1.11.1.dist-info/top_level.txt
ssh2_python3-1.11.1.dist-info/LICENSE
ssh2_python3-1.11.1.dist-info/METADATA
ssh2_python3-1.11.1.dist-info/WHEEL
ssh2_python3-1.11.1.dist-info/COPYING
ssh2/__init__.pxd
ssh2/channel.pyx
ssh2/publickey.pxd
ssh2/fileinfo.cpython-311-x86_64-linux-gnu.so
ssh2/sftp.pxd
ssh2/agent.pyx
ssh2/knownhost.pyx
ssh2/session.pyx
ssh2/sftp.cpython-311-x86_64-linux-gnu.so
ssh2/exceptions.cpython-311-x86_64-linux-gnu.so
ssh2/c_stat.pxd
ssh2/session.pxd
ssh2/c_sftp.pxd
ssh2/error_codes.pyx
ssh2/utils.cpython-311-x86_64-linux-gnu.so
ssh2/utils.pyx
ssh2/c_pkey.pxd
ssh2/listener.pyx
ssh2/error_codes.pxd
ssh2/_version.py
ssh2/statinfo.cpython-311-x86_64-linux-gnu.so
ssh2/agent.pxd
ssh2/session.cpython-311-x86_64-linux-gnu.so
ssh2/statinfo.pxd
ssh2/knownhost.cpython-311-x86_64-linux-gnu.so
ssh2/pkey.pxd
ssh2/channel.pxd
ssh2/error_codes.cpython-311-x86_64-linux-gnu.so
ssh2/utils.pxd
ssh2/sftp_handle.cpython-311-x86_64-linux-gnu.so
ssh2/listener.pxd
ssh2/listener.cpython-311-x86_64-linux-gnu.so
ssh2/agent.cpython-311-x86_64-linux-gnu.so
ssh2/publickey.cpython-311-x86_64-linux-gnu.so
ssh2/sftp.pyx
ssh2/__init__.py
ssh2/fileinfo.pxd
ssh2/pkey.pyx
ssh2/sftp_handle.pyx
ssh2/exceptions.pyx
ssh2/fileinfo.pyx
ssh2/publickey.pyx
ssh2/channel.cpython-311-x86_64-linux-gnu.so
ssh2/c_ssh2.pxd
ssh2/pkey.cpython-311-x86_64-linux-gnu.so
ssh2/sftp_handle.pxd
ssh2/knownhost.pxd
ssh2/statinfo.pyx
