Metadata-Version: 2.1
Name: ssh2-python3
Version: 1.11.1
Summary: Super fast SSH library - bindings for libssh2 and Python 3
Home-page: https://github.com/pycopia/ssh2-python3
Author: Panos Kittenis
Author-email: 22e889d8@opayq.com
Maintainer: Keith Dart
Maintainer-email: keith.dart@gmail.com
License: LGPLv2
Platform: linux_x86_64
Platform: manylinux2014_x86_64 
Classifier: Development Status :: 5 - Production/Stable
Classifier: License :: OSI Approved :: GNU Lesser General Public License v2 (LGPLv2)
Classifier: Intended Audience :: Developers
Classifier: Operating System :: OS Independent
Classifier: Programming Language :: C
Classifier: Programming Language :: Python
Classifier: Programming Language :: Python :: 3
Classifier: Programming Language :: Python :: 3 :: Only
Classifier: Programming Language :: Python :: 3.6
Classifier: Programming Language :: Python :: 3.7
Classifier: Programming Language :: Python :: 3.8
Classifier: Programming Language :: Python :: 3.9
Classifier: Topic :: System :: Shells
Classifier: Topic :: System :: Networking
Classifier: Topic :: Software Development :: Libraries
Classifier: Topic :: Software Development :: Libraries :: Python Modules
Classifier: Operating System :: POSIX
Classifier: Operating System :: POSIX :: Linux
Classifier: Operating System :: POSIX :: BSD
Requires-Python: >=3.8
License-File: LICENSE
License-File: COPYING
